unicornhathd/__init__.py
unicornhathd/unicornhathd.py
circuitpython_unicornhathd-0.6.1.dist-info/LICENSES/Unlicense.txt
circuitpython_unicornhathd-0.6.1.dist-info/LICENSE
circuitpython_unicornhathd-0.6.1.dist-info/LICENSES/MIT.txt
circuitpython_unicornhathd-0.6.1.dist-info/LICENSES/CC-BY-4.0.txt
circuitpython_unicornhathd-0.6.1.dist-info/WHEEL
circuitpython_unicornhathd-0.6.1.dist-info/METADATA
circuitpython_unicornhathd-0.6.1.dist-info/RECORD
