Metadata-Version: 2.1
Name: circuitpython-unicornhathd
Version: 0.6.1
Summary: CircuitPython framebuf based driver for Pimoroni's Unicorn HAT HD
Home-page: https://github.com/NathanY3G/CircuitPython_Unicorn_HAT_HD
License: MIT
Keywords: circuitpython,unicornhathd,unicorn-hat,unicorn-hat-hd
Author: Nathan Young
Requires-Python: >=3.6.2,<4.0.0
Classifier: License :: OSI Approved :: MIT License
Classifier: Programming Language :: Python :: 3
Classifier: Programming Language :: Python :: 3.10
Classifier: Programming Language :: Python :: 3.7
Classifier: Programming Language :: Python :: 3.8
Classifier: Programming Language :: Python :: 3.9
Requires-Dist: Adafruit-Blinka (>=6.15.0,<7.0.0)
Requires-Dist: adafruit-circuitpython-framebuf (>=1.4.7,<2.0.0)
Project-URL: Repository, https://github.com/NathanY3G/CircuitPython_Unicorn_HAT_HD
